tap_reviewscouk/__init__.py
tap_reviewscouk/schemas/merchant_reviews.json
tap_reviewscouk-0.0.2.dist-info/DESCRIPTION.rst
tap_reviewscouk-0.0.2.dist-info/METADATA
tap_reviewscouk-0.0.2.dist-info/RECORD
tap_reviewscouk-0.0.2.dist-info/WHEEL
tap_reviewscouk-0.0.2.dist-info/entry_points.txt
tap_reviewscouk-0.0.2.dist-info/metadata.json
tap_reviewscouk-0.0.2.dist-info/top_level.txt
